nebula_kubernetes/__init__.py
nebula_kubernetes/_version.py
nebula_kubernetes/credentials.py
nebula_kubernetes/custom_objects.py
nebula_kubernetes/deployments.py
nebula_kubernetes/events.py
nebula_kubernetes/exceptions.py
nebula_kubernetes/flows.py
nebula_kubernetes/jobs.py
nebula_kubernetes/pods.py
nebula_kubernetes/services.py
nebula_kubernetes/utilities.py
nebula_kubernetes/worker.py
nebula_kubernetes-1.0.0.dist-info/LICENSE
nebula_kubernetes-1.0.0.dist-info/METADATA
nebula_kubernetes-1.0.0.dist-info/WHEEL
nebula_kubernetes-1.0.0.dist-info/entry_points.txt
nebula_kubernetes-1.0.0.dist-info/top_level.txt
nebula_kubernetes-1.0.0.dist-info/RECORD
